zerolib/__init__.py
zerolib-0.0.0.dev1.dist-info/DESCRIPTION.rst
zerolib-0.0.0.dev1.dist-info/METADATA
zerolib-0.0.0.dev1.dist-info/RECORD
zerolib-0.0.0.dev1.dist-info/WHEEL
zerolib-0.0.0.dev1.dist-info/metadata.json
zerolib-0.0.0.dev1.dist-info/top_level.txt
